{
  "examDtoList": [
    {
      "classId": 1188,
      "className": "基金法律法规",
      "examId": 4716426,
      "paperInfo": null,
      "isRepeatTf": null,
      "answer": "D",
      "score": 0,
      "analysis": "金融市场的“市场失灵”问题主要表现为外部性问题、脆弱性问题、不完全竞争问题和信息不对称问题。",
      "content": "金融市场的“市场失灵”问题主要表现为（&emsp;&emsp;）。 <br />\nⅠ. 外部性问题 <br />\nⅡ. 脆弱性问题 <br />\nⅢ. 不完全竞争问题 <br />\nⅣ. 信息不对称问题 ",
      "questionArr": {
        "returnMaterial": "",
        "returnQuestion": "金融市场的“市场失灵”问题主要表现为（&emsp;&emsp;）。 <br />\nⅠ. 外部性问题 <br />\nⅡ. 脆弱性问题 <br />\nⅢ. 不完全竞争问题 <br />\nⅣ. 信息不对称问题 ",
        "returnOption": null
      },
      "examType": 1,
      "examTypeName": "单选题",
      "selectNum": 4,
      "linkExam": 0,
      "orderId": 1,
      "rulesId": 1800595,
      "diggUp": 0,
      "diggDown": 0,
      "weight": 0,
      "deNums": 3,
      "userDeNum": 0,
      "userDeNumStats": [
        7,
        5,
        13
      ],
      "discussCount": 33,
      "myDiscussCount": 0,
      "errorCount": 1,
      "expandPercent": "90",
      "expanddoExamNum": 160839,
      "favNum": 992,
      "isFavorites": false,
      "examNewStats": {
        "examId": 4716426,
        "lastDate": 1520695491,
        "recId": 0,
        "oldExamId": 0,
        "noteNum": 1,
        "analysisNum": 0,
        "examDoNum": 160839,
        "examFavNum": 992,
        "examRightNum": 144973,
        "examErrorNum": 15625,
        "maxWrongAnswer": "C,B",
        "isCloseError": false
      },
      "material": null,
      "optionList": [
        "Ⅰ、Ⅱ",
        "Ⅰ、Ⅳ",
        "Ⅱ、Ⅲ、Ⅳ",
        "Ⅰ、Ⅱ、Ⅲ、Ⅳ "
      ],
      "videoAnalysis": "",
      "videoAnalysisId": "",
      "videoCoverUrl": "//img2.233.com/m/vip/img/vedio.jpg",
      "userAnswer": "",
      "userScore": "0",
      "rightOrWrong": 0,
      "questionCount": 1,
      "md5": "041883f4b411ee64b1760d02ab057818",
      "isComputerApp": false,
      "subQuestion": [],
      "teacher": null,
      "knowledge": [
        {
          "knowLedgeId": 59091,
          "knowLedgeName": "金融市场的监管",
          "chapterName": "第1节",
          "parentChapterName": "第1章",
          "yaoQiu": 4,
          "yaoQiuName": "了解",
          "yaoQiuLevel": 1,
          "pageNum": "P9-10"
        }
      ],
      "scoreRules": {
        "examId": 4716426,
        "ruleScore": 1.0,
        "itemScore": 0.0,
        "errorScore": 0.0,
        "scoreRulesType": 1
      },
      "tikuId": 5003,
      "isCloseError": false,
      "isFree": true,
      "isOfficial": false,
      "officialYear": 0,
      "source": null,
      "historyAssessmentExamScoreV2Mongo": null,
      "hasKnow": -1
    },
    {
      "classId": 1188,
      "className": "基金法律法规",
      "examId": 4887249,
      "paperInfo": null,
      "isRepeatTf": null,
      "answer": "D",
      "score": 0,
      "analysis": "金融机构的业务性质决定了其高负债经营的特点。",
      "content": "金融机构的业务性质决定了其（&emsp;&emsp;）经营的特点。",
      "questionArr": {
        "returnMaterial": "",
        "returnQuestion": "金融机构的业务性质决定了其（&emsp;&emsp;）经营的特点。",
        "returnOption": null
      },
      "examType": 1,
      "examTypeName": "单选题",
      "selectNum": 4,
      "linkExam": 0,
      "orderId": 2,
      "rulesId": 1812335,
      "diggUp": 0,
      "diggDown": 0,
      "weight": 0,
      "deNums": 3,
      "userDeNum": 0,
      "userDeNumStats": [
        5,
        10,
        130
      ],
      "discussCount": 114,
      "myDiscussCount": 0,
      "errorCount": 4,
      "expandPercent": "51",
      "expanddoExamNum": 159897,
      "favNum": 2286,
      "isFavorites": false,
      "examNewStats": {
        "examId": 4887249,
        "lastDate": 1531430528,
        "recId": 0,
        "oldExamId": 0,
        "noteNum": 0,
        "analysisNum": 0,
        "examDoNum": 159897,
        "examFavNum": 2286,
        "examRightNum": 83008,
        "examErrorNum": 76706,
        "maxWrongAnswer": "A,B",
        "isCloseError": false
      },
      "material": null,
      "optionList": [
        "高流动",
        "低风险",
        "低收益",
        "高负债"
      ],
      "videoAnalysis": "",
      "videoAnalysisId": "",
      "videoCoverUrl": "//img2.233.com/m/vip/img/vedio.jpg",
      "userAnswer": "",
      "userScore": "0",
      "rightOrWrong": 0,
      "questionCount": 1,
      "md5": "041883f4b411ee64b1760d02ab057818",
      "isComputerApp": false,
      "subQuestion": [],
      "teacher": null,
      "knowledge": [
        {
          "knowLedgeId": 59091,
          "knowLedgeName": "金融市场的监管",
          "chapterName": "第1节",
          "parentChapterName": "第1章",
          "yaoQiu": 4,
          "yaoQiuName": "了解",
          "yaoQiuLevel": 1,
          "pageNum": "P9-10"
        }
      ],
      "scoreRules": {
        "examId": 4887249,
        "ruleScore": 1.0,
        "itemScore": 0.0,
        "errorScore": 0.0,
        "scoreRulesType": 1
      },
      "tikuId": 5003,
      "isCloseError": false,
      "isFree": true,
      "isOfficial": false,
      "officialYear": 0,
      "source": null,
      "historyAssessmentExamScoreV2Mongo": null,
      "hasKnow": -1
    },
    {
      "classId": 1188,
      "className": "基金法律法规",
      "examId": 4887260,
      "paperInfo": null,
      "isRepeatTf": null,
      "answer": "B",
      "score": 0,
      "analysis": "金融市场中，金融资产的无形性、金融交易的灵活性、金融行业的专业性等特点，决定了投资者、融资者和金融机构等参与主体之间的信息存在较为严重信息不对称问题，特别是广大的中小投资者容易受到不公平的对待，甚至被欺诈。",
      "content": "金融市场中，（&emsp;&emsp;）等特点，决定了参与主体之间的信息存在较为严重信息不对称问题。<br />\nⅠ．金融资产的无形性<br />\nⅡ．金融交易的灵活性<br />\nⅢ．金融交易的风险性<br />\nⅣ．金融行业的专业性",
      "questionArr": {
        "returnMaterial": "",
        "returnQuestion": "金融市场中，（&emsp;&emsp;）等特点，决定了参与主体之间的信息存在较为严重信息不对称问题。<br />\nⅠ．金融资产的无形性<br />\nⅡ．金融交易的灵活性<br />\nⅢ．金融交易的风险性<br />\nⅣ．金融行业的专业性",
        "returnOption": null
      },
      "examType": 1,
      "examTypeName": "单选题",
      "selectNum": 4,
      "linkExam": 0,
      "orderId": 3,
      "rulesId": 1812335,
      "diggUp": 0,
      "diggDown": 0,
      "weight": 0,
      "deNums": 3,
      "userDeNum": 0,
      "userDeNumStats": [
        3,
        8,
        148
      ],
      "discussCount": 130,
      "myDiscussCount": 0,
      "errorCount": 4,
      "expandPercent": "38",
      "expanddoExamNum": 178854,
      "favNum": 3079,
      "isFavorites": false,
      "examNewStats": {
        "examId": 4887260,
        "lastDate": 1531431217,
        "recId": 0,
        "oldExamId": 0,
        "noteNum": 3,
        "analysisNum": 0,
        "examDoNum": 178854,
        "examFavNum": 3079,
        "examRightNum": 68461,
        "examErrorNum": 110128,
        "maxWrongAnswer": "A,C",
        "isCloseError": false
      },
      "material": null,
      "optionList": [
        "Ⅰ、Ⅱ、Ⅲ、Ⅳ",
        "Ⅰ、Ⅱ、Ⅳ",
        "Ⅱ、Ⅲ、Ⅳ",
        "Ⅰ、Ⅲ、Ⅳ"
      ],
      "videoAnalysis": "",
      "videoAnalysisId": "",
      "videoCoverUrl": "//img2.233.com/m/vip/img/vedio.jpg",
      "userAnswer": "",
      "userScore": "0",
      "rightOrWrong": 0,
      "questionCount": 1,
      "md5": "041883f4b411ee64b1760d02ab057818",
      "isComputerApp": false,
      "subQuestion": [],
      "teacher": null,
      "knowledge": [
        {
          "knowLedgeId": 59091,
          "knowLedgeName": "金融市场的监管",
          "chapterName": "第1节",
          "parentChapterName": "第1章",
          "yaoQiu": 4,
          "yaoQiuName": "了解",
          "yaoQiuLevel": 1,
          "pageNum": "P9-10"
        }
      ],
      "scoreRules": {
        "examId": 4887260,
        "ruleScore": 1.0,
        "itemScore": 0.0,
        "errorScore": 0.0,
        "scoreRulesType": 1
      },
      "tikuId": 5003,
      "isCloseError": false,
      "isFree": true,
      "isOfficial": false,
      "officialYear": 0,
      "source": null,
      "historyAssessmentExamScoreV2Mongo": null,
      "hasKnow": -1
    },
    {
      "classId": 1188,
      "className": "基金法律法规",
      "examId": 4887261,
      "paperInfo": null,
      "isRepeatTf": null,
      "answer": "A",
      "score": 0,
      "analysis": "由于各国金融市场的具体情况不同，监管模式也不尽相同，有的国家采用政府集中型监管模式，有的采用行业自律型监管模式；有的国家实行不同金融行业的分业监管，有的实行各金融行业的统一监管。",
      "content": "各国政府对金融市场的监管模式有（&emsp;&emsp;）。<br />\nⅠ．政府集中型监管模式<br />\nⅡ．行业自律型监管模式<br />\nⅢ．不同金融行业的分业监管<br />\nⅣ．各金融行业的统一监管",
      "questionArr": {
        "returnMaterial": "",
        "returnQuestion": "各国政府对金融市场的监管模式有（&emsp;&emsp;）。<br />\nⅠ．政府集中型监管模式<br />\nⅡ．行业自律型监管模式<br />\nⅢ．不同金融行业的分业监管<br />\nⅣ．各金融行业的统一监管",
        "returnOption": null
      },
      "examType": 1,
      "examTypeName": "单选题",
      "selectNum": 4,
      "linkExam": 0,
      "orderId": 4,
      "rulesId": 1812335,
      "diggUp": 0,
      "diggDown": 0,
      "weight": 0,
      "deNums": 3,
      "userDeNum": 0,
      "userDeNumStats": [
        3,
        5,
        36
      ],
      "discussCount": 22,
      "myDiscussCount": 0,
      "errorCount": 1,
      "expandPercent": "83",
      "expanddoExamNum": 153476,
      "favNum": 1076,
      "isFavorites": false,
      "examNewStats": {
        "examId": 4887261,
        "lastDate": 1531431218,
        "recId": 0,
        "oldExamId": 0,
        "noteNum": 0,
        "analysisNum": 0,
        "examDoNum": 153476,
        "examFavNum": 1076,
        "examRightNum": 128887,
        "examErrorNum": 24432,
        "maxWrongAnswer": "B,C",
        "isCloseError": false
      },
      "material": null,
      "optionList": [
        "Ⅰ、Ⅱ、Ⅲ、Ⅳ",
        "Ⅰ、Ⅱ、Ⅳ",
        "Ⅱ、Ⅲ、Ⅳ",
        "Ⅰ、Ⅲ、Ⅳ"
      ],
      "videoAnalysis": "",
      "videoAnalysisId": "",
      "videoCoverUrl": "//img2.233.com/m/vip/img/vedio.jpg",
      "userAnswer": "",
      "userScore": "0",
      "rightOrWrong": 0,
      "questionCount": 1,
      "md5": "041883f4b411ee64b1760d02ab057818",
      "isComputerApp": false,
      "subQuestion": [],
      "teacher": null,
      "knowledge": [
        {
          "knowLedgeId": 59091,
          "knowLedgeName": "金融市场的监管",
          "chapterName": "第1节",
          "parentChapterName": "第1章",
          "yaoQiu": 4,
          "yaoQiuName": "了解",
          "yaoQiuLevel": 1,
          "pageNum": "P9-10"
        }
      ],
      "scoreRules": {
        "examId": 4887261,
        "ruleScore": 1.0,
        "itemScore": 0.0,
        "errorScore": 0.0,
        "scoreRulesType": 1
      },
      "tikuId": 5003,
      "isCloseError": false,
      "isFree": true,
      "isOfficial": false,
      "officialYear": 0,
      "source": null,
      "historyAssessmentExamScoreV2Mongo": null,
      "hasKnow": -1
    },
    {
      "classId": 1188,
      "className": "基金法律法规",
      "examId": 4574309,
      "paperInfo": null,
      "isRepeatTf": null,
      "answer": "D",
      "score": 0,
      "analysis": "金融市场的“市场失灵”问题主要表现为外部性问题、脆弱性问题、不完全竞争问题和信息不对称问题。",
      "content": "金融市场的“市场失灵”问题主要表现不包含（&emsp;&emsp;）。",
      "questionArr": {
        "returnMaterial": "",
        "returnQuestion": "金融市场的“市场失灵”问题主要表现不包含（&emsp;&emsp;）。",
        "returnOption": null
      },
      "examType": 1,
      "examTypeName": "单选题",
      "selectNum": 4,
      "linkExam": 0,
      "orderId": 5,
      "rulesId": 1859748,
      "diggUp": 0,
      "diggDown": 0,
      "weight": 0,
      "deNums": 3,
      "userDeNum": 0,
      "userDeNumStats": [
        4,
        9,
        38
      ],
      "discussCount": 46,
      "myDiscussCount": 0,
      "errorCount": 0,
      "expandPercent": "73",
      "expanddoExamNum": 68643,
      "favNum": 503,
      "isFavorites": false,
      "examNewStats": {
        "examId": 4574309,
        "lastDate": 0,
        "recId": 0,
        "oldExamId": 0,
        "noteNum": 0,
        "analysisNum": 0,
        "examDoNum": 68643,
        "examFavNum": 503,
        "examRightNum": 50672,
        "examErrorNum": 17786,
        "maxWrongAnswer": "C,B",
        "isCloseError": false
      },
      "material": null,
      "optionList": [
        "外部性问题",
        "脆弱性问题",
        "不完全竞争问题",
        "完全竞争问题"
      ],
      "videoAnalysis": "",
      "videoAnalysisId": "",
      "videoCoverUrl": "//img2.233.com/m/vip/img/vedio.jpg",
      "userAnswer": "",
      "userScore": "0",
      "rightOrWrong": 0,
      "questionCount": 1,
      "md5": "041883f4b411ee64b1760d02ab057818",
      "isComputerApp": false,
      "subQuestion": [],
      "teacher": null,
      "knowledge": [
        {
          "knowLedgeId": 59091,
          "knowLedgeName": "金融市场的监管",
          "chapterName": "第1节",
          "parentChapterName": "第1章",
          "yaoQiu": 4,
          "yaoQiuName": "了解",
          "yaoQiuLevel": 1,
          "pageNum": "P9-10"
        }
      ],
      "scoreRules": {
        "examId": 4574309,
        "ruleScore": 1.0,
        "itemScore": 0.0,
        "errorScore": 0.0,
        "scoreRulesType": 1
      },
      "tikuId": 5003,
      "isCloseError": false,
      "isFree": false,
      "isOfficial": false,
      "officialYear": 0,
      "source": null,
      "historyAssessmentExamScoreV2Mongo": null,
      "hasKnow": -1
    },
    {
      "classId": 1188,
      "className": "基金法律法规",
      "examId": 4659681,
      "paperInfo": null,
      "isRepeatTf": null,
      "answer": "A",
      "score": 0,
      "analysis": "金融市场是一个不完全竞争市场，金融机构特别是一些大型金融机构存在着一定程度的垄断，对金融市场价格具有一定程度的影响力甚至控制力，金融市场难以实现完全自由竞争。",
      "content": "金融市场是一个（&emsp;&emsp;）。",
      "questionArr": {
        "returnMaterial": "",
        "returnQuestion": "金融市场是一个（&emsp;&emsp;）。",
        "returnOption": null
      },
      "examType": 1,
      "examTypeName": "单选题",
      "selectNum": 4,
      "linkExam": 0,
      "orderId": 6,
      "rulesId": 1794390,
      "diggUp": 0,
      "diggDown": 0,
      "weight": 0,
      "deNums": 3,
      "userDeNum": 0,
      "userDeNumStats": [
        0,
        1,
        6
      ],
      "discussCount": 4,
      "myDiscussCount": 0,
      "errorCount": 1,
      "expandPercent": "81",
      "expanddoExamNum": 32061,
      "favNum": 98,
      "isFavorites": false,
      "examNewStats": {
        "examId": 4659681,
        "lastDate": 0,
        "recId": 0,
        "oldExamId": 0,
        "noteNum": 0,
        "analysisNum": 0,
        "examDoNum": 32061,
        "examFavNum": 98,
        "examRightNum": 26188,
        "examErrorNum": 5845,
        "maxWrongAnswer": "B,C",
        "isCloseError": false
      },
      "material": null,
      "optionList": [
        "不完全竞争市场",
        "完全竞争市场",
        "寡头垄断市场",
        "完全垄断市场"
      ],
      "videoAnalysis": "",
      "videoAnalysisId": "",
      "videoCoverUrl": "//img2.233.com/m/vip/img/vedio.jpg",
      "userAnswer": "",
      "userScore": "0",
      "rightOrWrong": 0,
      "questionCount": 1,
      "md5": "041883f4b411ee64b1760d02ab057818",
      "isComputerApp": false,
      "subQuestion": [],
      "teacher": null,
      "knowledge": [
        {
          "knowLedgeId": 59091,
          "knowLedgeName": "金融市场的监管",
          "chapterName": "第1节",
          "parentChapterName": "第1章",
          "yaoQiu": 4,
          "yaoQiuName": "了解",
          "yaoQiuLevel": 1,
          "pageNum": "P9-10"
        }
      ],
      "scoreRules": {
        "examId": 4659681,
        "ruleScore": 1.0,
        "itemScore": 0.0,
        "errorScore": 0.0,
        "scoreRulesType": 1
      },
      "tikuId": 5003,
      "isCloseError": false,
      "isFree": false,
      "isOfficial": false,
      "officialYear": 0,
      "source": null,
      "historyAssessmentExamScoreV2Mongo": null,
      "hasKnow": -1
    },
    {
      "classId": 1188,
      "className": "基金法律法规",
      "examId": 4659724,
      "paperInfo": null,
      "isRepeatTf": null,
      "answer": "D",
      "score": 0,
      "analysis": "根据我国相关法律规定，我国金融监管采取的是银行业、证券业、保险业分业监管的模式。故D项正确",
      "content": "根据我国相关法律规定，我国金融监管采取的是银行业、证券业、保险业（&emsp;&emsp;）的模式。",
      "questionArr": {
        "returnMaterial": "",
        "returnQuestion": "根据我国相关法律规定，我国金融监管采取的是银行业、证券业、保险业（&emsp;&emsp;）的模式。",
        "returnOption": null
      },
      "examType": 1,
      "examTypeName": "单选题",
      "selectNum": 4,
      "linkExam": 0,
      "orderId": 7,
      "rulesId": 1794390,
      "diggUp": 0,
      "diggDown": 0,
      "weight": 0,
      "deNums": 3,
      "userDeNum": 0,
      "userDeNumStats": [
        0,
        1,
        12
      ],
      "discussCount": 19,
      "myDiscussCount": 0,
      "errorCount": 1,
      "expandPercent": "69",
      "expanddoExamNum": 32360,
      "favNum": 140,
      "isFavorites": false,
      "examNewStats": {
        "examId": 4659724,
        "lastDate": 0,
        "recId": 0,
        "oldExamId": 0,
        "noteNum": 0,
        "analysisNum": 0,
        "examDoNum": 32360,
        "examFavNum": 140,
        "examRightNum": 22368,
        "examErrorNum": 9954,
        "maxWrongAnswer": "A,B",
        "isCloseError": false
      },
      "material": null,
      "optionList": [
        "统一监管",
        "集中监管",
        "宏观监管",
        "分业监管"
      ],
      "videoAnalysis": "",
      "videoAnalysisId": "",
      "videoCoverUrl": "//img2.233.com/m/vip/img/vedio.jpg",
      "userAnswer": "",
      "userScore": "0",
      "rightOrWrong": 0,
      "questionCount": 1,
      "md5": "041883f4b411ee64b1760d02ab057818",
      "isComputerApp": false,
      "subQuestion": [],
      "teacher": null,
      "knowledge": [
        {
          "knowLedgeId": 59091,
          "knowLedgeName": "金融市场的监管",
          "chapterName": "第1节",
          "parentChapterName": "第1章",
          "yaoQiu": 4,
          "yaoQiuName": "了解",
          "yaoQiuLevel": 1,
          "pageNum": "P9-10"
        }
      ],
      "scoreRules": {
        "examId": 4659724,
        "ruleScore": 1.0,
        "itemScore": 0.0,
        "errorScore": 0.0,
        "scoreRulesType": 1
      },
      "tikuId": 5003,
      "isCloseError": false,
      "isFree": false,
      "isOfficial": false,
      "officialYear": 0,
      "source": null,
      "historyAssessmentExamScoreV2Mongo": null,
      "hasKnow": -1
    },
    {
      "classId": 1188,
      "className": "基金法律法规",
      "examId": 4659742,
      "paperInfo": null,
      "isRepeatTf": null,
      "answer": "B",
      "score": 0,
      "analysis": "中国银行业监督管理机构、中国证券业监督管理机构、中国保险业监督管理机构分别对银行业金融机构、证券业金融机构、保险业金融机构及这些机构的业务活动实施监督管理。",
      "content": "下列金融市场的监管体系中，（&emsp;&emsp;）对证券业金融机构的业务活动实施监督管理。",
      "questionArr": {
        "returnMaterial": "",
        "returnQuestion": "下列金融市场的监管体系中，（&emsp;&emsp;）对证券业金融机构的业务活动实施监督管理。",
        "returnOption": null
      },
      "examType": 1,
      "examTypeName": "单选题",
      "selectNum": 4,
      "linkExam": 0,
      "orderId": 8,
      "rulesId": 1794390,
      "diggUp": 0,
      "diggDown": 0,
      "weight": 0,
      "deNums": 3,
      "userDeNum": 0,
      "userDeNumStats": [
        1,
        0,
        2
      ],
      "discussCount": 2,
      "myDiscussCount": 0,
      "errorCount": 0,
      "expandPercent": "88",
      "expanddoExamNum": 31625,
      "favNum": 142,
      "isFavorites": false,
      "examNewStats": {
        "examId": 4659742,
        "lastDate": 0,
        "recId": 0,
        "oldExamId": 0,
        "noteNum": 0,
        "analysisNum": 0,
        "examDoNum": 31625,
        "examFavNum": 142,
        "examRightNum": 27854,
        "examErrorNum": 3745,
        "maxWrongAnswer": "B,A",
        "isCloseError": false
      },
      "material": null,
      "optionList": [
        "中国银行业监督管理机构",
        "中国证券业监督管理机构",
        "中国保险业监督管理机构",
        "中国人民银行"
      ],
      "videoAnalysis": "",
      "videoAnalysisId": "",
      "videoCoverUrl": "//img2.233.com/m/vip/img/vedio.jpg",
      "userAnswer": "",
      "userScore": "0",
      "rightOrWrong": 0,
      "questionCount": 1,
      "md5": "041883f4b411ee64b1760d02ab057818",
      "isComputerApp": false,
      "subQuestion": [],
      "teacher": null,
      "knowledge": [
        {
          "knowLedgeId": 59091,
          "knowLedgeName": "金融市场的监管",
          "chapterName": "第1节",
          "parentChapterName": "第1章",
          "yaoQiu": 4,
          "yaoQiuName": "了解",
          "yaoQiuLevel": 1,
          "pageNum": "P9-10"
        }
      ],
      "scoreRules": {
        "examId": 4659742,
        "ruleScore": 1.0,
        "itemScore": 0.0,
        "errorScore": 0.0,
        "scoreRulesType": 1
      },
      "tikuId": 5003,
      "isCloseError": false,
      "isFree": false,
      "isOfficial": false,
      "officialYear": 0,
      "source": null,
      "historyAssessmentExamScoreV2Mongo": null,
      "hasKnow": -1
    }
  ],
  "md5": "041883f4b411ee64b1760d02ab057818",
  "examTime": 0,
  "mode": 1,
  "class": 0,
  "objectId": 0,
  "pageIndex": 1,
  "count": 8,
  "extractType": 0,
  "isKnowledge": false,
  "examType": null,
  "status": 0,
  "startOrderId": 0,
  "fistFreeOrderId": 0,
  "listPageMap": [
    {
      "start": 1,
      "end": 8
    }
  ],
  "rootClassName": null,
  "examName": null,
  "className": null,
  "useTime": 0,
  "myClassId": 0,
  "dcourseId": 0,
  "zuheMyClassId": 0,
  "teacherId": 0,
  "year": 0,
  "historyTitle": null,
  "parentId": 0,
  "productId": 0
}