{
  "examDtoList": [
    {
      "classId": 1189,
      "className": "证券投资基金基础知识",
      "examId": 4662974,
      "paperInfo": null,
      "isRepeatTf": null,
      "answer": "C",
      "score": 0,
      "analysis": "\n选项C符合题意：基金业绩评价应遵循客观性、可比性、长期性原则。<br />\n考点<br />\n基金业绩评价的原则&nbsp;<br />\n",
      "content": "\n下列关于基金业绩评价原则的说法错误的是（）。",
      "questionArr": {
        "returnMaterial": "",
        "returnQuestion": "\n下列关于基金业绩评价原则的说法错误的是（）。",
        "returnOption": null
      },
      "examType": 1,
      "examTypeName": "单选题",
      "selectNum": 4,
      "linkExam": 0,
      "orderId": 1,
      "rulesId": 1846067,
      "diggUp": 0,
      "diggDown": 0,
      "weight": 0,
      "deNums": 3,
      "userDeNum": 0,
      "userDeNumStats": [
        0,
        0,
        2
      ],
      "discussCount": 14,
      "myDiscussCount": 0,
      "errorCount": 1,
      "expandPercent": "57",
      "expanddoExamNum": 21888,
      "favNum": 132,
      "isFavorites": false,
      "examNewStats": {
        "examId": 4662974,
        "lastDate": 0,
        "recId": 0,
        "oldExamId": 0,
        "noteNum": 0,
        "analysisNum": 0,
        "examDoNum": 21888,
        "examFavNum": 132,
        "examRightNum": 12665,
        "examErrorNum": 9172,
        "maxWrongAnswer": "A,D",
        "isCloseError": false
      },
      "material": null,
      "optionList": [
        "基金业绩评价应将同类基金的风险收益交换效率进行比较",
        "基金业绩评价应公平对待所有评价对象",
        "基金业绩评价应遵循客观性、可比性、长期性、公开性原则",
        "基金业绩评价只有坚持长期性原则，才能真正着眼于基金长期投资管理能力的持续性"
      ],
      "videoAnalysis": "",
      "videoAnalysisId": "",
      "videoCoverUrl": "//img2.233.com/m/vip/img/vedio.jpg",
      "userAnswer": "",
      "userScore": "0",
      "rightOrWrong": 0,
      "questionCount": 1,
      "md5": "00149b3f7cfc1fc2a973f278cca8c56d",
      "isComputerApp": false,
      "subQuestion": [],
      "teacher": null,
      "knowledge": [
        {
          "knowLedgeId": 57506,
          "knowLedgeName": "投资业绩评价的原则",
          "chapterName": "第1节",
          "parentChapterName": "第15章",
          "yaoQiu": 3,
          "yaoQiuName": "掌握",
          "yaoQiuLevel": 3,
          "pageNum": "P453-P454"
        }
      ],
      "scoreRules": {
        "examId": 4662974,
        "ruleScore": 1.0,
        "itemScore": 0.0,
        "errorScore": 0.0,
        "scoreRulesType": 1
      },
      "tikuId": 5004,
      "isCloseError": false,
      "isFree": true,
      "isOfficial": false,
      "officialYear": 0,
      "source": null,
      "historyAssessmentExamScoreV2Mongo": null,
      "hasKnow": -1
    },
    {
      "classId": 1189,
      "className": "证券投资基金基础知识",
      "examId": 4886222,
      "paperInfo": null,
      "isRepeatTf": null,
      "answer": "A",
      "score": 0,
      "analysis": "基金业绩评价应遵循如下原则：<br />\n(1)客观性原则，(2)可比性原则，(3)长期性原则。<br />\n知识点：掌握投资业绩评价的目的、原则和应该考虑的因素：",
      "content": "基金业绩评价应遵循如下原则( )。 <br />\nⅠ 客观性原则 <br />\nⅡ 可比性原则 <br />\nⅢ 长期性原则 <br />\nⅣ 真实性原则",
      "questionArr": {
        "returnMaterial": "",
        "returnQuestion": "基金业绩评价应遵循如下原则( )。 <br />\nⅠ 客观性原则 <br />\nⅡ 可比性原则 <br />\nⅢ 长期性原则 <br />\nⅣ 真实性原则",
        "returnOption": null
      },
      "examType": 1,
      "examTypeName": "单选题",
      "selectNum": 4,
      "linkExam": 0,
      "orderId": 2,
      "rulesId": 1846067,
      "diggUp": 0,
      "diggDown": 0,
      "weight": 0,
      "deNums": 3,
      "userDeNum": 0,
      "userDeNumStats": [
        0,
        0,
        1
      ],
      "discussCount": 4,
      "myDiscussCount": 0,
      "errorCount": 0,
      "expandPercent": "84",
      "expanddoExamNum": 22944,
      "favNum": 121,
      "isFavorites": false,
      "examNewStats": {
        "examId": 4886222,
        "lastDate": 1531411316,
        "recId": 0,
        "oldExamId": 0,
        "noteNum": 0,
        "analysisNum": 0,
        "examDoNum": 22944,
        "examFavNum": 121,
        "examRightNum": 19279,
        "examErrorNum": 3619,
        "maxWrongAnswer": "B,C",
        "isCloseError": false
      },
      "material": null,
      "optionList": [
        "Ⅰ、Ⅱ、Ⅲ",
        "Ⅰ、Ⅱ、Ⅳ",
        "Ⅰ、Ⅲ、Ⅳ",
        "Ⅱ、Ⅲ、Ⅳ "
      ],
      "videoAnalysis": "",
      "videoAnalysisId": "",
      "videoCoverUrl": "//img2.233.com/m/vip/img/vedio.jpg",
      "userAnswer": "",
      "userScore": "0",
      "rightOrWrong": 0,
      "questionCount": 1,
      "md5": "00149b3f7cfc1fc2a973f278cca8c56d",
      "isComputerApp": false,
      "subQuestion": [],
      "teacher": null,
      "knowledge": [
        {
          "knowLedgeId": 57506,
          "knowLedgeName": "投资业绩评价的原则",
          "chapterName": "第1节",
          "parentChapterName": "第15章",
          "yaoQiu": 3,
          "yaoQiuName": "掌握",
          "yaoQiuLevel": 3,
          "pageNum": "P453-P454"
        }
      ],
      "scoreRules": {
        "examId": 4886222,
        "ruleScore": 1.0,
        "itemScore": 0.0,
        "errorScore": 0.0,
        "scoreRulesType": 1
      },
      "tikuId": 5004,
      "isCloseError": false,
      "isFree": true,
      "isOfficial": false,
      "officialYear": 0,
      "source": null,
      "historyAssessmentExamScoreV2Mongo": null,
      "hasKnow": -1
    }
  ],
  "md5": "00149b3f7cfc1fc2a973f278cca8c56d",
  "examTime": 0,
  "mode": 1,
  "class": 0,
  "objectId": 0,
  "pageIndex": 1,
  "count": 2,
  "extractType": 0,
  "isKnowledge": false,
  "examType": null,
  "status": 0,
  "startOrderId": 0,
  "fistFreeOrderId": 0,
  "listPageMap": [
    {
      "start": 1,
      "end": 2
    }
  ],
  "rootClassName": null,
  "examName": null,
  "className": null,
  "useTime": 0,
  "myClassId": 0,
  "dcourseId": 0,
  "zuheMyClassId": 0,
  "teacherId": 0,
  "year": 0,
  "historyTitle": null,
  "parentId": 0,
  "productId": 0
}