{
  "examDtoList": [
    {
      "classId": 1188,
      "className": "基金法律法规",
      "examId": 4664291,
      "paperInfo": null,
      "isRepeatTf": null,
      "answer": "B",
      "score": 0,
      "analysis": "基金的运作活动从基金管理人的角度看，可以分为基金的市场营销、基金的投资管理与基金的后台管理三大部分。其中，基金的市场营销主要涉及基金份额的募集与客户服务。",
      "content": "(       )主要涉及基金份额的募集与客户服务。 ",
      "questionArr": {
        "returnMaterial": "",
        "returnQuestion": "(       )主要涉及基金份额的募集与客户服务。 ",
        "returnOption": null
      },
      "examType": 1,
      "examTypeName": "单选题",
      "selectNum": 4,
      "linkExam": 0,
      "orderId": 1,
      "rulesId": 1805784,
      "diggUp": 0,
      "diggDown": 0,
      "weight": 0,
      "deNums": 3,
      "userDeNum": 0,
      "userDeNumStats": [
        2,
        2,
        16
      ],
      "discussCount": 25,
      "myDiscussCount": 0,
      "errorCount": 1,
      "expandPercent": "72",
      "expanddoExamNum": 69192,
      "favNum": 710,
      "isFavorites": false,
      "examNewStats": {
        "examId": 4664291,
        "lastDate": 0,
        "recId": 0,
        "oldExamId": 0,
        "noteNum": 0,
        "analysisNum": 0,
        "examDoNum": 69192,
        "examFavNum": 710,
        "examRightNum": 49894,
        "examErrorNum": 19226,
        "maxWrongAnswer": "C,D",
        "isCloseError": false
      },
      "material": null,
      "optionList": [
        "基金的产品开发",
        "基金的市场营销",
        "基金的投资管理",
        "基金的后台管理 "
      ],
      "videoAnalysis": "",
      "videoAnalysisId": "",
      "videoCoverUrl": "//img2.233.com/m/vip/img/vedio.jpg",
      "userAnswer": "",
      "userScore": "0",
      "rightOrWrong": 0,
      "questionCount": 1,
      "md5": "f67270577c9594dc11a26a57033f7375",
      "isComputerApp": false,
      "subQuestion": [],
      "teacher": null,
      "knowledge": [
        {
          "knowLedgeId": 57258,
          "knowLedgeName": "证券投资基金的运作",
          "chapterName": "第2节",
          "parentChapterName": "第2章",
          "yaoQiu": 4,
          "yaoQiuName": "了解",
          "yaoQiuLevel": 1,
          "pageNum": "P32"
        }
      ],
      "scoreRules": {
        "examId": 4664291,
        "ruleScore": 1.0,
        "itemScore": 0.0,
        "errorScore": 0.0,
        "scoreRulesType": 1
      },
      "tikuId": 5003,
      "isCloseError": false,
      "isFree": true,
      "isOfficial": false,
      "officialYear": 0,
      "source": null,
      "historyAssessmentExamScoreV2Mongo": null,
      "hasKnow": -1
    },
    {
      "classId": 1188,
      "className": "基金法律法规",
      "examId": 4574367,
      "paperInfo": null,
      "isRepeatTf": null,
      "answer": "A",
      "score": 0,
      "analysis": "基金的市场营销主要涉及基金份额的募集与客户服务，基金的投资管理体现了基金管理人的服务价值，而基金份额的注册登记、基金资产的估值、会计核算、信息披露等后台管理服务则对保障基金的安全运作起着重要的作用。",
      "content": "基金的后台管理运作不包括（&emsp;&emsp;）。",
      "questionArr": {
        "returnMaterial": "",
        "returnQuestion": "基金的后台管理运作不包括（&emsp;&emsp;）。",
        "returnOption": null
      },
      "examType": 1,
      "examTypeName": "单选题",
      "selectNum": 4,
      "linkExam": 0,
      "orderId": 2,
      "rulesId": 1859748,
      "diggUp": 0,
      "diggDown": 0,
      "weight": 0,
      "deNums": 3,
      "userDeNum": 0,
      "userDeNumStats": [
        1,
        1,
        5
      ],
      "discussCount": 6,
      "myDiscussCount": 0,
      "errorCount": 0,
      "expandPercent": "75",
      "expanddoExamNum": 26500,
      "favNum": 179,
      "isFavorites": false,
      "examNewStats": {
        "examId": 4574367,
        "lastDate": 0,
        "recId": 0,
        "oldExamId": 0,
        "noteNum": 0,
        "analysisNum": 0,
        "examDoNum": 26500,
        "examFavNum": 179,
        "examRightNum": 20113,
        "examErrorNum": 6325,
        "maxWrongAnswer": "D,C",
        "isCloseError": false
      },
      "material": null,
      "optionList": [
        "基金份额的销售",
        "基金会计核算和信息披露",
        "基金资产的估值",
        "基金份额的注册登记"
      ],
      "videoAnalysis": "",
      "videoAnalysisId": "",
      "videoCoverUrl": "//img2.233.com/m/vip/img/vedio.jpg",
      "userAnswer": "",
      "userScore": "0",
      "rightOrWrong": 0,
      "questionCount": 1,
      "md5": "f67270577c9594dc11a26a57033f7375",
      "isComputerApp": false,
      "subQuestion": [],
      "teacher": null,
      "knowledge": [
        {
          "knowLedgeId": 57258,
          "knowLedgeName": "证券投资基金的运作",
          "chapterName": "第2节",
          "parentChapterName": "第2章",
          "yaoQiu": 4,
          "yaoQiuName": "了解",
          "yaoQiuLevel": 1,
          "pageNum": "P32"
        }
      ],
      "scoreRules": {
        "examId": 4574367,
        "ruleScore": 1.0,
        "itemScore": 0.0,
        "errorScore": 0.0,
        "scoreRulesType": 1
      },
      "tikuId": 5003,
      "isCloseError": false,
      "isFree": false,
      "isOfficial": false,
      "officialYear": 0,
      "source": null,
      "historyAssessmentExamScoreV2Mongo": null,
      "hasKnow": -1
    },
    {
      "classId": 1188,
      "className": "基金法律法规",
      "examId": 4657829,
      "paperInfo": null,
      "isRepeatTf": null,
      "answer": "B",
      "score": 0,
      "analysis": "B项符合题意：基金的运作包括基金的募集、基金的投资管理、基金资产的托管、基金份额的登记交易、基金的估值与会计核算、基金的信息披露以及其他基金运作活动在内的所有相关环节。",
      "content": "基金的运作包括（       ）。<br />\nⅠ、基金的募集<br />\nⅡ、基金的投资管理<br />\nⅢ、基金资产的托管<br />\nⅣ、基金份额的登记交易",
      "questionArr": {
        "returnMaterial": "",
        "returnQuestion": "基金的运作包括（       ）。<br />\nⅠ、基金的募集<br />\nⅡ、基金的投资管理<br />\nⅢ、基金资产的托管<br />\nⅣ、基金份额的登记交易",
        "returnOption": null
      },
      "examType": 1,
      "examTypeName": "单选题",
      "selectNum": 4,
      "linkExam": 0,
      "orderId": 3,
      "rulesId": 1794355,
      "diggUp": 0,
      "diggDown": 0,
      "weight": 0,
      "deNums": 3,
      "userDeNum": 0,
      "userDeNumStats": [
        0,
        0,
        0
      ],
      "discussCount": 2,
      "myDiscussCount": 0,
      "errorCount": 1,
      "expandPercent": "91",
      "expanddoExamNum": 12605,
      "favNum": 16,
      "isFavorites": false,
      "examNewStats": {
        "examId": 4657829,
        "lastDate": 0,
        "recId": 0,
        "oldExamId": 0,
        "noteNum": 0,
        "analysisNum": 0,
        "examDoNum": 12605,
        "examFavNum": 16,
        "examRightNum": 11497,
        "examErrorNum": 1090,
        "maxWrongAnswer": "D,A",
        "isCloseError": false
      },
      "material": null,
      "optionList": [
        "Ⅰ、Ⅲ、Ⅳ",
        "Ⅰ、Ⅱ、Ⅲ、Ⅳ",
        "Ⅱ、Ⅲ、Ⅳ",
        "Ⅰ、Ⅱ、Ⅲ"
      ],
      "videoAnalysis": "",
      "videoAnalysisId": "",
      "videoCoverUrl": "//img2.233.com/m/vip/img/vedio.jpg",
      "userAnswer": "",
      "userScore": "0",
      "rightOrWrong": 0,
      "questionCount": 1,
      "md5": "f67270577c9594dc11a26a57033f7375",
      "isComputerApp": false,
      "subQuestion": [],
      "teacher": null,
      "knowledge": [
        {
          "knowLedgeId": 57258,
          "knowLedgeName": "证券投资基金的运作",
          "chapterName": "第2节",
          "parentChapterName": "第2章",
          "yaoQiu": 4,
          "yaoQiuName": "了解",
          "yaoQiuLevel": 1,
          "pageNum": "P32"
        }
      ],
      "scoreRules": {
        "examId": 4657829,
        "ruleScore": 1.0,
        "itemScore": 0.0,
        "errorScore": 0.0,
        "scoreRulesType": 1
      },
      "tikuId": 5003,
      "isCloseError": false,
      "isFree": false,
      "isOfficial": false,
      "officialYear": 0,
      "source": null,
      "historyAssessmentExamScoreV2Mongo": null,
      "hasKnow": -1
    },
    {
      "classId": 1188,
      "className": "基金法律法规",
      "examId": 4657843,
      "paperInfo": null,
      "isRepeatTf": null,
      "answer": "B",
      "score": 0,
      "analysis": "基金的运作活动从基金管理人的角度看，可以分为基金的市场营销、基金的投资管理与基金的后台管理三大部分。",
      "content": "基金的运作活动从基金管理人的角度看，可以分为（       ）。<br />\nⅠ、基金的市场营销<br />\nⅡ、基金的盈亏核算<br />\nⅢ、基金的投资管理<br />\nⅣ、基金的后台管理",
      "questionArr": {
        "returnMaterial": "",
        "returnQuestion": "基金的运作活动从基金管理人的角度看，可以分为（       ）。<br />\nⅠ、基金的市场营销<br />\nⅡ、基金的盈亏核算<br />\nⅢ、基金的投资管理<br />\nⅣ、基金的后台管理",
        "returnOption": null
      },
      "examType": 1,
      "examTypeName": "单选题",
      "selectNum": 4,
      "linkExam": 0,
      "orderId": 4,
      "rulesId": 1794355,
      "diggUp": 0,
      "diggDown": 0,
      "weight": 0,
      "deNums": 3,
      "userDeNum": 0,
      "userDeNumStats": [
        0,
        1,
        1
      ],
      "discussCount": 9,
      "myDiscussCount": 0,
      "errorCount": 2,
      "expandPercent": "46",
      "expanddoExamNum": 13398,
      "favNum": 80,
      "isFavorites": false,
      "examNewStats": {
        "examId": 4657843,
        "lastDate": 0,
        "recId": 0,
        "oldExamId": 0,
        "noteNum": 0,
        "analysisNum": 0,
        "examDoNum": 13398,
        "examFavNum": 80,
        "examRightNum": 6189,
        "examErrorNum": 7195,
        "maxWrongAnswer": "D,A",
        "isCloseError": false
      },
      "material": null,
      "optionList": [
        "Ⅰ、Ⅱ、Ⅲ",
        "Ⅰ、Ⅲ、Ⅳ",
        "Ⅱ、Ⅲ、Ⅳ",
        "Ⅰ、Ⅱ、Ⅲ、Ⅳ"
      ],
      "videoAnalysis": "",
      "videoAnalysisId": "",
      "videoCoverUrl": "//img2.233.com/m/vip/img/vedio.jpg",
      "userAnswer": "",
      "userScore": "0",
      "rightOrWrong": 0,
      "questionCount": 1,
      "md5": "f67270577c9594dc11a26a57033f7375",
      "isComputerApp": false,
      "subQuestion": [],
      "teacher": null,
      "knowledge": [
        {
          "knowLedgeId": 57258,
          "knowLedgeName": "证券投资基金的运作",
          "chapterName": "第2节",
          "parentChapterName": "第2章",
          "yaoQiu": 4,
          "yaoQiuName": "了解",
          "yaoQiuLevel": 1,
          "pageNum": "P32"
        }
      ],
      "scoreRules": {
        "examId": 4657843,
        "ruleScore": 1.0,
        "itemScore": 0.0,
        "errorScore": 0.0,
        "scoreRulesType": 1
      },
      "tikuId": 5003,
      "isCloseError": false,
      "isFree": false,
      "isOfficial": false,
      "officialYear": 0,
      "source": null,
      "historyAssessmentExamScoreV2Mongo": null,
      "hasKnow": -1
    },
    {
      "classId": 1188,
      "className": "基金法律法规",
      "examId": 4657951,
      "paperInfo": null,
      "isRepeatTf": null,
      "answer": "D",
      "score": 0,
      "analysis": "选项D符合题意：Ⅲ项，基金的投资管理体现了基金管理人的服务价值。基金份额的注册登记，基金资产的估值，基金的信息披露等后台管理服务对保障基金的安全运作起着重要的作用。",
      "content": "（       ）等后台管理服务对保障基金的安全运作起着重要的作用。<br />\nⅠ、基金份额的注册登记<br />\nⅡ、基金资产的估值<br />\nⅢ、基金的投资管理<br />\nⅣ、基金的信息披露",
      "questionArr": {
        "returnMaterial": "",
        "returnQuestion": "（       ）等后台管理服务对保障基金的安全运作起着重要的作用。<br />\nⅠ、基金份额的注册登记<br />\nⅡ、基金资产的估值<br />\nⅢ、基金的投资管理<br />\nⅣ、基金的信息披露",
        "returnOption": null
      },
      "examType": 1,
      "examTypeName": "单选题",
      "selectNum": 4,
      "linkExam": 0,
      "orderId": 5,
      "rulesId": 1794355,
      "diggUp": 0,
      "diggDown": 0,
      "weight": 0,
      "deNums": 3,
      "userDeNum": 0,
      "userDeNumStats": [
        0,
        0,
        5
      ],
      "discussCount": 6,
      "myDiscussCount": 0,
      "errorCount": 1,
      "expandPercent": "52",
      "expanddoExamNum": 13305,
      "favNum": 80,
      "isFavorites": false,
      "examNewStats": {
        "examId": 4657951,
        "lastDate": 0,
        "recId": 0,
        "oldExamId": 0,
        "noteNum": 0,
        "analysisNum": 0,
        "examDoNum": 13305,
        "examFavNum": 80,
        "examRightNum": 6991,
        "examErrorNum": 6306,
        "maxWrongAnswer": "A,C",
        "isCloseError": false
      },
      "material": null,
      "optionList": [
        "Ⅰ、Ⅲ、Ⅳ",
        "Ⅰ、Ⅱ、Ⅲ",
        "Ⅱ、Ⅲ、Ⅳ",
        "Ⅰ、Ⅱ、Ⅳ"
      ],
      "videoAnalysis": "",
      "videoAnalysisId": "",
      "videoCoverUrl": "//img2.233.com/m/vip/img/vedio.jpg",
      "userAnswer": "",
      "userScore": "0",
      "rightOrWrong": 0,
      "questionCount": 1,
      "md5": "f67270577c9594dc11a26a57033f7375",
      "isComputerApp": false,
      "subQuestion": [],
      "teacher": null,
      "knowledge": [
        {
          "knowLedgeId": 57258,
          "knowLedgeName": "证券投资基金的运作",
          "chapterName": "第2节",
          "parentChapterName": "第2章",
          "yaoQiu": 4,
          "yaoQiuName": "了解",
          "yaoQiuLevel": 1,
          "pageNum": "P32"
        }
      ],
      "scoreRules": {
        "examId": 4657951,
        "ruleScore": 1.0,
        "itemScore": 0.0,
        "errorScore": 0.0,
        "scoreRulesType": 1
      },
      "tikuId": 5003,
      "isCloseError": false,
      "isFree": false,
      "isOfficial": false,
      "officialYear": 0,
      "source": null,
      "historyAssessmentExamScoreV2Mongo": null,
      "hasKnow": -1
    }
  ],
  "md5": "f67270577c9594dc11a26a57033f7375",
  "examTime": 0,
  "mode": 1,
  "class": 0,
  "objectId": 0,
  "pageIndex": 1,
  "count": 5,
  "extractType": 0,
  "isKnowledge": false,
  "examType": null,
  "status": 0,
  "startOrderId": 0,
  "fistFreeOrderId": 0,
  "listPageMap": [
    {
      "start": 1,
      "end": 5
    }
  ],
  "rootClassName": null,
  "examName": null,
  "className": null,
  "useTime": 0,
  "myClassId": 0,
  "dcourseId": 0,
  "zuheMyClassId": 0,
  "teacherId": 0,
  "year": 0,
  "historyTitle": null,
  "parentId": 0,
  "productId": 0
}